qwed_ucp/__init__.py
qwed_ucp/core.py
qwed_ucp/guards/__init__.py
qwed_ucp/guards/currency.py
qwed_ucp/guards/discount.py
qwed_ucp/guards/line_items.py
qwed_ucp/guards/money.py
qwed_ucp/guards/schema.py
qwed_ucp/guards/state.py
qwed_ucp/middleware/__init__.py
qwed_ucp/middleware/fastapi.py
qwed_ucp-0.2.0.dist-info/METADATA
qwed_ucp-0.2.0.dist-info/WHEEL
qwed_ucp-0.2.0.dist-info/licenses/LICENSE
qwed_ucp-0.2.0.dist-info/RECORD
