Metadata-Version: 2.4
Name: qwed-ucp
Version: 0.2.0
Summary: QWED verification for Universal Commerce Protocol (UCP) transactions
Project-URL: Homepage, https://github.com/QWED-AI/qwed-ucp
Project-URL: Documentation, https://github.com/QWED-AI/qwed-ucp#readme
Project-URL: Repository, https://github.com/QWED-AI/qwed-ucp
Author-email: Rahul Dass <rahul@qwedai.com>
License: Apache-2.0
License-File: LICENSE
Keywords: ai,commerce,google,llm,qwed,ucp,verification
Classifier: Development Status :: 3 - Alpha
Classifier: Intended Audience :: Developers
Classifier: License :: OSI Approved :: Apache Software License
Classifier: Programming Language :: Python :: 3
Classifier: Programming Language :: Python :: 3.10
Classifier: Programming Language :: Python :: 3.11
Classifier: Programming Language :: Python :: 3.12
Requires-Python: >=3.10
Requires-Dist: jsonschema>=4.0.0
Provides-Extra: dev
Requires-Dist: pytest-cov>=4.0.0; extra == 'dev'
Requires-Dist: pytest>=7.0.0; extra == 'dev'
